[
 {
   "Site": "Newnham Meadows",
   "Area": 5.89,
   "Ownership": "PCC"
 },
 {
   "Site": "Radford Woods",
   "Area": 40.21,
   "Ownership": "PCC"
 },
 {
   "Site": "Ham Woods",
   "Area": 35.93,
   "Ownership": "PCC"
 },
 {
   "Site": "Kings Tamerton",
   "Area": 7.82,
   "Ownership": "PCC"
 },
 {
   "Site": "Southway Valley",
   "Area": 15.77,
   "Ownership": "PCC"
 },
 {
   "Site": "Cann Woods",
   "Area": 23.42,
   "Ownership": "PCC"
 },
 {
   "Site": "Whitleigh Woods",
   "Area": 20.18,
   "Ownership": "Woodland Trust"
 },
 {
   "Site": "Budshead Wood",
   "Area": 14.68,
   "Ownership": "PCC"
 },
 {
   "Site": "Efford Marsh",
   "Area": 25.08,
   "Ownership": "PCC"
 },
 {
   "Site": "Seaton and Lower Bircham",
   "Area": 33.23,
   "Ownership": "PCC"
 },
 {
   "Site": "Bircham Valley",
   "Area": 23.87,
   "Ownership": "PCC"
 },
 {
   "Site": "Forder Valley",
   "Area": 26.14,
   "Ownership": "PCC"
 },
 {
   "Site": "Woodland Wood",
   "Area": 29.67,
   "Ownership": "PCC"
 }
]